ksbus/__init__.py
ksbus/client.py
ksbus-1.3.1.dist-info/LICENSE
ksbus-1.3.1.dist-info/METADATA
ksbus-1.3.1.dist-info/WHEEL
ksbus-1.3.1.dist-info/top_level.txt
ksbus-1.3.1.dist-info/RECORD
