Metadata-Version: 2.1
Name: ksbus
Version: 1.3.1
Summary: Ksbus client for https://github.com/kamalshkeir/ksbus
Author: Ksbus (Kamal Shkeir)
Author-email: <kamalshkeir@gmail.com>
Keywords: eventbus,bus,ksbus,korm,pubsub,websockets,ws
Classifier: Development Status :: 5 - Production/Stable
Classifier: Intended Audience :: Developers
Classifier: Programming Language :: Python :: 3
Classifier: Operating System :: Unix
Classifier: Operating System :: MacOS :: MacOS X
Classifier: Operating System :: Microsoft :: Windows
License-File: LICENSE
Requires-Dist: asyncio
Requires-Dist: websockets
